ziopy/VERSION
ziopy/__init__.py
ziopy/either.py
ziopy/environments.py
ziopy/hlist.py
ziopy/py.typed
ziopy/util.py
ziopy/validation.py
ziopy/zio.py
ziopy/services/__init__.py
ziopy/services/console.py
ziopy/services/system.py
ziopy/services/mock_effects/__init__.py
ziopy/services/mock_effects/console.py
ziopy/services/mock_effects/system.py
zio_py-0.0.16.dist-info/LICENSE
zio_py-0.0.16.dist-info/METADATA
zio_py-0.0.16.dist-info/WHEEL
zio_py-0.0.16.dist-info/top_level.txt
zio_py-0.0.16.dist-info/RECORD
