Metadata-Version: 2.1
Name: zio-py
Version: 0.0.16
Summary: Python port of Scala ZIO for pure functional programming
Home-page: https://github.com/miiohio/ziopy
Author: William Harvey
Author-email: drwjharvey@gmail.com
License: MIT License
Platform: UNKNOWN
Requires-Dist: typing-extensions (>=4.6.1)
Requires-Dist: dataclasses ; python_version < "3.7"
